sphinx_apa_references/__init__.py
sphinx_apa_references/_version.py
sphinx_apa_references/assets/apastyle.css
sphinx_apa_references-1.0.1.dist-info/METADATA
sphinx_apa_references-1.0.1.dist-info/WHEEL
sphinx_apa_references-1.0.1.dist-info/licenses/LICENSE
sphinx_apa_references-1.0.1.dist-info/RECORD
