Metadata-Version: 2.4
Name: sphinx-apa-references
Version: 1.0.1
Summary: A simple Sphinx extension that allows you to have APA formatting of references in your book.
Author-email: Dennis den Ouden-van der Horst <d.denouden-vanderhorst@tudelft.nl>, Robert Lanzafame <lanzafame.robert@gmail.com>
License-File: LICENSE
Requires-Python: >=3.10
Requires-Dist: pybtex
Requires-Dist: sphinx
